dnskeeper/__init__.py
dnskeeper/__main__.py
dnskeeper/cloudflare.py
dnskeeper/dnskeeper.py
dnskeeper/local.py
dnskeeper-1.0.0.dist-info/DESCRIPTION.rst
dnskeeper-1.0.0.dist-info/METADATA
dnskeeper-1.0.0.dist-info/RECORD
dnskeeper-1.0.0.dist-info/WHEEL
dnskeeper-1.0.0.dist-info/entry_points.txt
dnskeeper-1.0.0.dist-info/metadata.json
dnskeeper-1.0.0.dist-info/top_level.txt
