Metadata-Version: 2.0
Name: dnskeeper
Version: 1.0.0
Summary: Tool for managing DNS records in cloudflare and storing them locally in JSON.
Home-page: https://github.com/liftedkilt/dnskeeper-cloudflare
Author: William Forsyth
Author-email: william.forsyth@liferay.com
License: BSD-2-Clause
Platform: UNKNOWN
Requires-Dist: CloudFlare
Requires-Dist: tabulate
